gerapy_prometheus_exporter/__init__.py
gerapy_prometheus_exporter/__version__.py
gerapy_prometheus_exporter/extension.py
gerapy_prometheus_exporter/settings.py
gerapy_prometheus_exporter-0.1.0.dist-info/METADATA
gerapy_prometheus_exporter-0.1.0.dist-info/WHEEL
gerapy_prometheus_exporter-0.1.0.dist-info/top_level.txt
gerapy_prometheus_exporter-0.1.0.dist-info/RECORD
